aibanking/__init__.py
aibanking/_base_client.py
aibanking/_client.py
aibanking/_compat.py
aibanking/_constants.py
aibanking/_exceptions.py
aibanking/_files.py
aibanking/_models.py
aibanking/_qs.py
aibanking/_resource.py
aibanking/_response.py
aibanking/_streaming.py
aibanking/_types.py
aibanking/_version.py
aibanking/py.typed
aibanking/_utils/__init__.py
aibanking/_utils/_compat.py
aibanking/_utils/_datetime_parse.py
aibanking/_utils/_logs.py
aibanking/_utils/_proxy.py
aibanking/_utils/_reflection.py
aibanking/_utils/_resources_proxy.py
aibanking/_utils/_streams.py
aibanking/_utils/_sync.py
aibanking/_utils/_transform.py
aibanking/_utils/_typing.py
aibanking/_utils/_utils.py
aibanking/lib/.keep
aibanking/resources/__init__.py
aibanking/resources/accounts/__init__.py
aibanking/resources/accounts/accounts.py
aibanking/resources/accounts/overdraft_settings.py
aibanking/resources/accounts/statements.py
aibanking/resources/accounts/transactions.py
aibanking/resources/ai/__init__.py
aibanking/resources/ai/ai.py
aibanking/resources/ai/models.py
aibanking/resources/ai/ads/__init__.py
aibanking/resources/ai/ads/ads.py
aibanking/resources/ai/ads/generate.py
aibanking/resources/ai/advisor/__init__.py
aibanking/resources/ai/advisor/advisor.py
aibanking/resources/ai/advisor/chat.py
aibanking/resources/ai/advisor/tools.py
aibanking/resources/ai/agent/__init__.py
aibanking/resources/ai/agent/agent.py
aibanking/resources/ai/agent/prompts.py
aibanking/resources/ai/incubator/__init__.py
aibanking/resources/ai/incubator/analysis.py
aibanking/resources/ai/incubator/incubator.py
aibanking/resources/ai/incubator/pitch.py
aibanking/resources/ai/oracle/__init__.py
aibanking/resources/ai/oracle/oracle.py
aibanking/resources/ai/oracle/predictions.py
aibanking/resources/ai/oracle/simulate.py
aibanking/resources/ai/oracle/simulations.py
aibanking/resources/corporate/__init__.py
aibanking/resources/corporate/anomalies.py
aibanking/resources/corporate/cards.py
aibanking-0.13.0.dist-info/METADATA
aibanking-0.13.0.dist-info/WHEEL
aibanking-0.13.0.dist-info/licenses/LICENSE
aibanking-0.13.0.dist-info/RECORD
